django_hashedpass/__init__.py
django_hashedpass/management/__init__.py
django_hashedpass/management/commands/__init__.py
django_hashedpass/management/commands/changehashedpass.py
django_hashedpass/management/commands/genhashedpass.py
django_hashedpass-0.1.0.dist-info/LICENSE
django_hashedpass-0.1.0.dist-info/METADATA
django_hashedpass-0.1.0.dist-info/WHEEL
django_hashedpass-0.1.0.dist-info/top_level.txt
django_hashedpass-0.1.0.dist-info/RECORD
