Metadata-Version: 2.1
Name: django-hashedpass
Version: 0.1.0
Summary: Django management commands for changing users' hashed passwords.
Home-page: https://github.com/cwfoo/django-hashedpass
Author: Foo Chuan Wei
Author-email: chuanwei.foo@hotmail.com
License: BSD 3-Clause License
Platform: UNKNOWN
Classifier: Environment :: Web Environment
Classifier: Framework :: Django
Classifier: Intended Audience :: Developers
Classifier: License :: OSI Approved :: BSD License
Classifier: Operating System :: OS Independent
Classifier: Programming Language :: Python
Classifier: Programming Language :: Python :: 3
Classifier: Programming Language :: Python :: 3 :: Only
Classifier: Topic :: Software Development :: Libraries :: Python Modules
Requires-Python: >=3.5
Requires-Dist: Django (>=2.2)
